vridgeai/__init__.py
vridgeai/data_preprocessing.py
vridgeai/database_utils.py
vridgeai/dataset_utils.py
vridgeai/model_utils.py
vridgeai/test.py
vridgeai-0.2.8.dist-info/METADATA
vridgeai-0.2.8.dist-info/WHEEL
vridgeai-0.2.8.dist-info/top_level.txt
vridgeai-0.2.8.dist-info/RECORD
