Metadata-Version: 2.1
Name: vridgeai
Version: 0.2.8
Summary: vridgeai python package
Author: byungchan
Author-email: bgk@vazilcompany.com
Keywords: vazil,vazilcompany,vridge,vridgeai
Classifier: Programming Language :: Python :: 3.7
Classifier: Programming Language :: Python :: 3.8
Classifier: Programming Language :: Python :: 3.9
Requires-Python: >=3.7, <3.10
Requires-Dist: tensorflow ==2.6.0
Requires-Dist: keras ==2.6.0
Requires-Dist: protobuf ==3.20.0
Requires-Dist: numpy ==1.19.3
Requires-Dist: matplotlib ==3.3.4
Requires-Dist: python-dotenv
Requires-Dist: requests
